kbputils/__init__.py
kbputils/__main__.py
kbputils/_ffmpegcolor.py
kbputils/cli.py
kbputils/doblontxt.py
kbputils/kbp.py
kbputils/kbpfont.py
kbputils/kbs.py
kbputils/lrc.py
kbputils/validators.py
kbputils/converters/__init__.py
kbputils/converters/ass2video.py
kbputils/converters/kbp2ass.py
kbputils/converters/lyrics2kbp.py
kbputils/misc/__init__.py
kbputils/misc/kbpcheck.py
kbputils-0.2.10.dist-info/licenses/LICENSE
kbputils-0.2.10.dist-info/METADATA
kbputils-0.2.10.dist-info/WHEEL
kbputils-0.2.10.dist-info/entry_points.txt
kbputils-0.2.10.dist-info/top_level.txt
kbputils-0.2.10.dist-info/RECORD
