Metadata-Version: 2.4
Name: kbputils
Version: 0.2.10
Summary: Utilities to handle .kbp files created with Karaoke Builder Studio.
Author-email: Matt M <code@itmightbekaraoke.com>
Classifier: Development Status :: 3 - Alpha
Classifier: License :: OSI Approved :: BSD License
Requires-Python: >=3.11
License-File: LICENSE
Requires-Dist: ass
Requires-Dist: charset-normalizer
Provides-Extra: ffmpeg
Requires-Dist: ffmpeg-python; extra == "ffmpeg"
Dynamic: license-file
